.travis.yml
MANIFEST.in
changelog.md
contributing.md
license.md
readme.md
requirements.txt
setup.py
bin/jasy
bin/jasy-doc
bin/jasy-doc.bat
bin/jasy-style-util.py
bin/jasy-test
bin/jasy-test.bat
bin/jasy-util
bin/jasy-util.bat
bin/jasy.bat
jasy/__init__.py
jasy.egg-info/PKG-INFO
jasy.egg-info/SOURCES.txt
jasy.egg-info/dependency_links.txt
jasy.egg-info/requires.txt
jasy.egg-info/top_level.txt
jasy/abstract/Resolver.py
jasy/abstract/Sorter.py
jasy/abstract/__init__.py
jasy/asset/ImageInfo.py
jasy/asset/Manager.py
jasy/asset/SpritePacker.py
jasy/asset/__init__.py
jasy/asset/sprite/Block.py
jasy/asset/sprite/BlockNode.py
jasy/asset/sprite/BlockPacker.py
jasy/asset/sprite/File.py
jasy/asset/sprite/Sheet.py
jasy/asset/sprite/__init__.py
jasy/core/Base62.py
jasy/core/Cache.py
jasy/core/Config.py
jasy/core/Console.py
jasy/core/Create.py
jasy/core/Doctor.py
jasy/core/File.py
jasy/core/FileManager.py
jasy/core/FlagSet.py
jasy/core/Inspect.py
jasy/core/Locale.py
jasy/core/MetaData.py
jasy/core/Options.py
jasy/core/OutputManager.py
jasy/core/Permutation.py
jasy/core/Profile.py
jasy/core/Project.py
jasy/core/Session.py
jasy/core/Text.py
jasy/core/Types.py
jasy/core/Util.py
jasy/core/__init__.py
jasy/data/cldr/VERSION
jasy/data/cldr/keys/C.xml
jasy/data/cldr/keys/de.xml
jasy/data/cldr/keys/es.xml
jasy/data/cldr/keys/fr.xml
jasy/data/cldr/keys/it.xml
jasy/data/cldr/keys/nl.xml
jasy/data/cldr/keys/pl.xml
jasy/data/cldr/keys/sv.xml
jasy/data/cldr/main/aa.xml
jasy/data/cldr/main/aa_DJ.xml
jasy/data/cldr/main/aa_ER.xml
jasy/data/cldr/main/aa_ET.xml
jasy/data/cldr/main/af.xml
jasy/data/cldr/main/af_NA.xml
jasy/data/cldr/main/af_ZA.xml
jasy/data/cldr/main/agq.xml
jasy/data/cldr/main/agq_CM.xml
jasy/data/cldr/main/ak.xml
jasy/data/cldr/main/ak_GH.xml
jasy/data/cldr/main/am.xml
jasy/data/cldr/main/am_ET.xml
jasy/data/cldr/main/ar.xml
jasy/data/cldr/main/ar_001.xml
jasy/data/cldr/main/ar_AE.xml
jasy/data/cldr/main/ar_BH.xml
jasy/data/cldr/main/ar_DZ.xml
jasy/data/cldr/main/ar_EG.xml
jasy/data/cldr/main/ar_IQ.xml
jasy/data/cldr/main/ar_JO.xml
jasy/data/cldr/main/ar_KW.xml
jasy/data/cldr/main/ar_LB.xml
